{
  "players": [
    {
      "id": "731977d7-3863-4ff7-af00-1cc16447f944",
      "created_at": "2019-03-04T16:29:54-05:00",
      "updated_at": "2019-03-09T13:06:59-05:00",
      "active": true,
      "bats": "bats_unknown",
      "birth_date": null,
      "captain": null,
      "city": null,
      "country": "",
      "draft_overall_pick": null,
      "draft_round": null,
      "draft_season": null,
      "draft_team_name": null,
      "first_name": "Roldani",
      "handedness": "unknown",
      "height": null,
      "high_school": null,
      "humanized_salary": "0",
      "last_name": "Baldwin",
      "mlbam_id": null,
      "name": "",
      "nickname": "Roldani",
      "position_abbreviation": "C",
      "position_name": "C",
      "pro_debut": null,
      "salary": null,
      "salary_currency": "USD",
      "school": null,
      "slug": "mlb-0fe2eea0-002a-4373-aad6-f2072558c2f5",
      "sport": "baseball",
      "state": "",
      "uniform_number": null,
      "unit_of_height": "inches",
      "unit_of_weight": "pounds",
      "weight": null,
      "years_of_experience": null,
      "league_id": "cb399a17-e581-4f1a-9535-ea3bcb09fa1f",
      "playing_position_id": null,
      "team_id": "4c2ad3df-a7fd-458d-a412-6e31574a0b7b"
    },
    {
      "id": "6c2978fe-b241-42c7-aa7d-607f1b5bc1cc",
      "created_at": "2016-03-18T21:10:30-04:00",
      "updated_at": "2019-04-19T20:14:34-04:00",
      "active": true,
      "bats": "bats_right",
      "birth_date": "1990-06-17",
      "captain": null,
      "city": "Danbury",
      "country": "",
      "draft_overall_pick": 19,
      "draft_round": 1,
      "draft_season": "2011",
      "draft_team_name": null,
      "first_name": "Matthew",
      "handedness": "right",
      "height": 76,
      "high_school": "Bethel (CT)",
      "humanized_salary": "511,000",
      "last_name": "Barnes",
      "mlbam_id": 598264,
      "name": "",
      "nickname": "Matt",
      "position_abbreviation": "RP",
      "position_name": "Reliever",
      "pro_debut": "2014-09-09",
      "salary": 511000,
      "salary_currency": "USD",
      "school": "Connecticut",
      "slug": "mlb-matt-barnes",
      "sport": "baseball",
      "state": "",
      "uniform_number": "32",
      "unit_of_height": "inches",
      "unit_of_weight": "pounds",
      "weight": 210,
      "years_of_experience": 3,
      "league_id": "cb399a17-e581-4f1a-9535-ea3bcb09fa1f",
      "playing_position_id": "e895b7e6-2178-41d8-8666-bb4c1bedd2ad",
      "team_id": "4c2ad3df-a7fd-458d-a412-6e31574a0b7b"
    },
    {
      "id": "14d3cdd3-422e-4efd-9d0c-b61718ef76f6",
      "created_at": "2016-07-14T02:27:23-04:00",
      "updated_at": "2019-04-19T20:14:33-04:00",
      "active": true,
      "bats": "bats_left",
      "birth_date": "1994-07-06",
      "captain": null,
      "city": "Cincinnati",
      "country": "",
      "draft_overall_pick": null,
      "draft_round": null,
      "draft_season": null,
      "draft_team_name": null,
      "first_name": "Andrew",
      "handedness": "left",
      "height": 70,
      "high_school": "Madeira (OH)",
      "humanized_salary": "0",
      "last_name": "Benintendi",
      "mlbam_id": 643217,
      "name": "",
      "nickname": "Andrew",
      "position_abbreviation": "OF",
      "position_name": "OF",
      "pro_debut": "2016-08-02",
      "salary": null,
      "salary_currency": "USD",
      "school": "Arkansas",
      "slug": "andrew-benintendi",
      "sport": "baseball",
      "state": "",
      "uniform_number": "16",
      "unit_of_height": "inches",
      "unit_of_weight": "pounds",
      "weight": 170,
      "years_of_experience": null,
      "league_id": "cb399a17-e581-4f1a-9535-ea3bcb09fa1f",
      "playing_position_id": null,
      "team_id": "4c2ad3df-a7fd-458d-a412-6e31574a0b7b"
    },
    {
      "id": "bfca5f98-d7ca-47b9-a7dc-f9848e334cea",
      "created_at": "2016-03-18T21:10:30-04:00",
      "updated_at": "2019-04-19T20:14:32-04:00",
      "active": true,
      "bats": "bats_right",
      "birth_date": "1992-10-07",
      "captain": null,
      "city": "Nashville",
      "country": "",
      "draft_overall_pick": 172,
      "draft_round": 5,
      "draft_season": "2011",
      "draft_team_name": null,
      "first_name": "Markus",
      "handedness": "right",
      "height": 69,
      "high_school": "John Overton (TN)",
      "humanized_salary": "566,000",
      "last_name": "Betts",
      "mlbam_id": 605141,
      "name": "",
      "nickname": "Mookie",
      "position_abbreviation": "RF",
      "position_name": "Right Outfield",
      "pro_debut": "2014-06-29",
      "salary": 566000,
      "salary_currency": "USD",
      "school": null,
      "slug": "mlb-mookie-betts",
      "sport": "baseball",
      "state": "",
      "uniform_number": "50",
      "unit_of_height": "inches",
      "unit_of_weight": "pounds",
      "weight": 180,
      "years_of_experience": 3,
      "league_id": "cb399a17-e581-4f1a-9535-ea3bcb09fa1f",
      "playing_position_id": "77303dac-3e19-4c49-802c-eef8719d26cf",
      "team_id": "4c2ad3df-a7fd-458d-a412-6e31574a0b7b"
    },
    {
      "id": "88861b5b-76b5-43dc-bbad-b2c2aea72a8a",
      "created_at": "2016-03-18T21:10:30-04:00",
      "updated_at": "2019-04-19T20:14:33-04:00",
      "active": true,
      "bats": "bats_right",
      "birth_date": "1992-10-01",
      "captain": null,
      "city": "Oranjestad",
      "country": "",
      "draft_overall_pick": null,
      "draft_round": null,
      "draft_season": null,
      "draft_team_name": null,
      "first_name": "Xander",
      "handedness": "right",
      "height": 73,
      "high_school": "Colegio Arubano (ABW)",
      "humanized_salary": "650,600",
      "last_name": "Bogaerts",
      "mlbam_id": 593428,
      "name": "",
      "nickname": "Xander",
      "position_abbreviation": "SS",
      "position_name": "Shortstop",
      "pro_debut": "2013-08-20",
      "salary": 650600,
      "salary_currency": "USD",
      "school": null,
      "slug": "mlb-xander-bogaerts",
      "sport": "baseball",
      "state": "",
      "uniform_number": "2",
      "unit_of_height": "inches",
      "unit_of_weight": "pounds",
      "weight": 210,
      "years_of_experience": 4,
      "league_id": "cb399a17-e581-4f1a-9535-ea3bcb09fa1f",
      "playing_position_id": "4b5f1bc6-07c1-442b-9228-cd9ff0f5b8d1",
      "team_id": "4c2ad3df-a7fd-458d-a412-6e31574a0b7b"
    },
    {
      "id": "bed54f1c-83f5-4373-93d5-a88df57c0550",
      "created_at": "2016-03-18T21:10:30-04:00",
      "updated_at": "2019-04-19T20:14:33-04:00",
      "active": true,
      "bats": "bats_left",
      "birth_date": "1990-04-19",
      "captain": null,
      "city": "Richmond",
      "country": "",
      "draft_overall_pick": 40,
      "draft_round": 1,
      "draft_season": "2011",
      "draft_team_name": null,
      "first_name": "Jackie",
      "handedness": "right",
      "height": 70,
      "high_school": "Prince George, Prince George, VA",
      "humanized_salary": "546,500",
      "last_name": "Bradley Jr.",
      "mlbam_id": 598265,
      "name": "",
      "nickname": "Jackie",
      "position_abbreviation": "CF",
      "position_name": "Center Outfield",
      "pro_debut": "2013-04-01",
      "salary": 546500,
      "salary_currency": "USD",
      "school": "South Carolina",
      "slug": "mlb-jackie-bradley-jr",
      "sport": "baseball",
      "state": "",
      "uniform_number": "19",
      "unit_of_height": "inches",
      "unit_of_weight": "pounds",
      "weight": 200,
      "years_of_experience": 4,
      "league_id": "cb399a17-e581-4f1a-9535-ea3bcb09fa1f",
      "playing_position_id": "e900e850-ab40-4048-aa57-631ea8390519",
      "team_id": "4c2ad3df-a7fd-458d-a412-6e31574a0b7b"
    },
    {
      "id": "5f0de0a2-a52e-470e-bcf8-dd59a5c406cf",
      "created_at": "2016-07-14T02:13:17-04:00",
      "updated_at": "2019-04-19T20:14:33-04:00",
      "active": true,
      "bats": "bats_right",
      "birth_date": "1987-08-26",
      "captain": null,
      "city": "Wichita Falls",
      "country": "",
      "draft_overall_pick": null,
      "draft_round": null,
      "draft_season": null,
      "draft_team_name": null,
      "first_name": "Ryan",
      "handedness": "right",
      "height": 72,
      "high_school": "Rider, Wichita Falls, TX",
      "humanized_salary": "0",
      "last_name": "Brasier",
      "mlbam_id": 518489,
      "name": "",
      "nickname": "Ryan",
      "position_abbreviation": "P",
      "position_name": "P",
      "pro_debut": "2013-05-02",
      "salary": null,
      "salary_currency": "USD",
      "school": "Weatherford CC, Weatherford, TX",
      "slug": "ryan-brasier",
      "sport": "baseball",
      "state": "",
      "uniform_number": "70",
      "unit_of_height": "inches",
      "unit_of_weight": "pounds",
      "weight": 225,
      "years_of_experience": null,
      "league_id": "cb399a17-e581-4f1a-9535-ea3bcb09fa1f",
      "playing_position_id": null,
      "team_id": "4c2ad3df-a7fd-458d-a412-6e31574a0b7b"
    },
    {
      "id": "a0d7b12b-5965-4b36-bbcf-73f4c4849e2a",
      "created_at": "2016-03-18T21:10:31-04:00",
      "updated_at": "2019-03-19T14:01:07-04:00",
      "active": true,
      "bats": "bats_right",
      "birth_date": "1988-12-30",
      "captain": null,
      "city": "Crossville",
      "country": "",
      "draft_overall_pick": 36,
      "draft_round": 1,
      "draft_season": "2010",
      "draft_team_name": "Boston",
      "first_name": "Bryce",
      "handedness": "right",
      "height": 72,
      "high_school": "South Doyle, Knoxville, TN",
      "humanized_salary": "507,500",
      "last_name": "Brentz",
      "mlbam_id": 518490,
      "name": "",
      "nickname": "Bryce",
      "position_abbreviation": "RF",
      "position_name": "Right Outfield",
      "pro_debut": "2014-09-17",
      "salary": 507500,
      "salary_currency": "USD",
      "school": "Middle Tennessee State, Murfreesboro, TN",
      "slug": "mlb-bryce-brentz",
      "sport": "baseball",
      "state": "",
      "uniform_number": "54",
      "unit_of_height": "inches",
      "unit_of_weight": "pounds",
      "weight": 210,
      "years_of_experience": 1,
      "league_id": "cb399a17-e581-4f1a-9535-ea3bcb09fa1f",
      "playing_position_id": "77303dac-3e19-4c49-802c-eef8719d26cf",
      "team_id": "4c2ad3df-a7fd-458d-a412-6e31574a0b7b"
    },
    {
      "id": "45caff13-c86a-48aa-8de5-44da882a05cc",
      "created_at": "2018-02-22T10:08:07-05:00",
      "updated_at": "2019-04-19T20:14:34-04:00",
      "active": true,
      "bats": "bats_right",
      "birth_date": "1992-10-29",
      "captain": null,
      "city": "Dallas",
      "country": "",
      "draft_overall_pick": null,
      "draft_round": null,
      "draft_season": null,
      "draft_team_name": null,
      "first_name": "Colten",
      "handedness": "right",
      "height": 76,
      "high_school": "Canton, TX",
      "humanized_salary": "0",
      "last_name": "Brewer",
      "mlbam_id": 605155,
      "name": "",
      "nickname": "Colten",
      "position_abbreviation": "P",
      "position_name": "P",
      "pro_debut": "2018-04-12",
      "salary": null,
      "salary_currency": "USD",
      "school": null,
      "slug": "mlb-colten-brewer",
      "sport": "baseball",
      "state": "",
      "uniform_number": "54",
      "unit_of_height": "inches",
      "unit_of_weight": "pounds",
      "weight": 230,
      "years_of_experience": null,
      "league_id": "cb399a17-e581-4f1a-9535-ea3bcb09fa1f",
      "playing_position_id": null,
      "team_id": "4c2ad3df-a7fd-458d-a412-6e31574a0b7b"
    },
    {
      "id": "518ca203-58a0-4285-bb3a-6bfb486d7593",
      "created_at": "2016-03-18T21:09:28-04:00",
      "updated_at": "2019-03-20T14:02:18-04:00",
      "active": true,
      "bats": "bats_left",
      "birth_date": "1989-11-16",
      "captain": null,
      "city": "Arecibo",
      "country": "",
      "draft_overall_pick": null,
      "draft_round": null,
      "draft_season": null,
      "draft_team_name": null,
      "first_name": "Juan",
      "handedness": "right",
      "height": 70,
      "high_school": "Antonio Luchettii, Arecibo, PR",
      "humanized_salary": "507,500",
      "last_name": "Centeno",
      "mlbam_id": 518542,
      "name": "",
      "nickname": "Juan",
      "position_abbreviation": "C",
      "position_name": "Catcher",
      "pro_debut": "2013-09-18",
      "salary": 507500,
      "salary_currency": "USD",
      "school": null,
      "slug": "mlb-juan-centeno",
      "sport": "baseball",
      "state": "",
      "uniform_number": "68",
      "unit_of_height": "inches",
      "unit_of_weight": "pounds",
      "weight": 170,
      "years_of_experience": 1,
      "league_id": "cb399a17-e581-4f1a-9535-ea3bcb09fa1f",
      "playing_position_id": "35d2f5d0-7407-48c2-80ca-8e5d25e099d9",
      "team_id": "4c2ad3df-a7fd-458d-a412-6e31574a0b7b"
    },
    {
      "id": "3fd91bf9-94dd-4184-a157-07f6d5c6b958",
      "created_at": "2019-02-27T13:17:55-05:00",
      "updated_at": "2019-03-20T14:02:30-04:00",
      "active": true,
      "bats": "bats_unknown",
      "birth_date": null,
      "captain": null,
      "city": null,
      "country": "",
      "draft_overall_pick": null,
      "draft_round": null,
      "draft_season": null,
      "draft_team_name": null,
      "first_name": "Connor",
      "handedness": "unknown",
      "height": null,
      "high_school": null,
      "humanized_salary": "0",
      "last_name": "Chatham",
      "mlbam_id": null,
      "name": "",
      "nickname": "C.J.",
      "position_abbreviation": "IF",
      "position_name": "IF",
      "pro_debut": null,
      "salary": null,
      "salary_currency": "USD",
      "school": null,
      "slug": "mlb-fa70973f-d544-43aa-8ed9-33243f77c339",
      "sport": "baseball",
      "state": "",
      "uniform_number": "90",
      "unit_of_height": "inches",
      "unit_of_weight": "pounds",
      "weight": null,
      "years_of_experience": null,
      "league_id": "cb399a17-e581-4f1a-9535-ea3bcb09fa1f",
      "playing_position_id": null,
      "team_id": "4c2ad3df-a7fd-458d-a412-6e31574a0b7b"
    },
    {
      "id": "65301106-5df0-4e45-b95d-62a0893b0b8b",
      "created_at": "2019-02-23T15:02:59-05:00",
      "updated_at": "2019-04-19T20:14:32-04:00",
      "active": true,
      "bats": "bats_right",
      "birth_date": "1995-08-11",
      "captain": null,
      "city": "Marietta",
      "country": "",
      "draft_overall_pick": null,
      "draft_round": null,
      "draft_season": null,
      "draft_team_name": null,
      "first_name": "Michael",
      "handedness": "right",
      "height": 70,
      "high_school": "Sprayberry, Marietta, GA",
      "humanized_salary": "0",
      "last_name": "Chavis",
      "mlbam_id": 656308,
      "name": "",
      "nickname": "Michael",
      "position_abbreviation": "IF",
      "position_name": "IF",
      "pro_debut": null,
      "salary": null,
      "salary_currency": "USD",
      "school": null,
      "slug": "mlb-michael-chavis",
      "sport": "baseball",
      "state": "",
      "uniform_number": "23",
      "unit_of_height": "inches",
      "unit_of_weight": "pounds",
      "weight": 216,
      "years_of_experience": null,
      "league_id": "cb399a17-e581-4f1a-9535-ea3bcb09fa1f",
      "playing_position_id": null,
      "team_id": "4c2ad3df-a7fd-458d-a412-6e31574a0b7b"
    },
    {
      "id": "01a04264-958e-4f0e-bc69-16e9c1f07cbb",
      "created_at": "2019-02-24T15:54:09-05:00",
      "updated_at": "2019-03-01T13:07:42-05:00",
      "active": true,
      "bats": "bats_unknown",
      "birth_date": null,
      "captain": null,
      "city": null,
      "country": "",
      "draft_overall_pick": null,
      "draft_round": null,
      "draft_season": null,
      "draft_team_name": null,
      "first_name": "Kutter",
      "handedness": "unknown",
      "height": null,
      "high_school": null,
      "humanized_salary": "0",
      "last_name": "Crawford",
      "mlbam_id": null,
      "name": "",
      "nickname": "Kutter",
      "position_abbreviation": "P",
      "position_name": "P",
      "pro_debut": null,
      "salary": null,
      "salary_currency": "USD",
      "school": null,
      "slug": "mlb-4cebb11d-c9f5-42bd-94a2-7331f998b05e",
      "sport": "baseball",
      "state": "",
      "uniform_number": null,
      "unit_of_height": "inches",
      "unit_of_weight": "pounds",
      "weight": null,
      "years_of_experience": null,
      "league_id": "cb399a17-e581-4f1a-9535-ea3bcb09fa1f",
      "playing_position_id": null,
      "team_id": "4c2ad3df-a7fd-458d-a412-6e31574a0b7b"
    },
    {
      "id": "07000391-d992-4741-9657-45f515ce0cd6",
      "created_at": "2019-02-27T16:13:27-05:00",
      "updated_at": "2019-03-04T13:08:41-05:00",
      "active": true,
      "bats": "bats_unknown",
      "birth_date": null,
      "captain": null,
      "city": null,
      "country": "",
      "draft_overall_pick": null,
      "draft_round": null,
      "draft_season": null,
      "draft_team_name": null,
      "first_name": "Keith",
      "handedness": "unknown",
      "height": null,
      "high_school": null,
      "humanized_salary": "0",
      "last_name": "Curcio",
      "mlbam_id": null,
      "name": "",
      "nickname": "Keith",
      "position_abbreviation": "OF",
      "position_name": "OF",
      "pro_debut": null,
      "salary": null,
      "salary_currency": "USD",
      "school": null,
      "slug": "mlb-45bd33a2-08cd-44bd-846f-b62ca9ef0e11",
      "sport": "baseball",
      "state": "",
      "uniform_number": "46",
      "unit_of_height": "inches",
      "unit_of_weight": "pounds",
      "weight": null,
      "years_of_experience": null,
      "league_id": "cb399a17-e581-4f1a-9535-ea3bcb09fa1f",
      "playing_position_id": null,
      "team_id": "4c2ad3df-a7fd-458d-a412-6e31574a0b7b"
    },
    {
      "id": "00ffaeee-8275-466f-ba59-cd69df4ba179",
      "created_at": "2019-02-24T14:34:34-05:00",
      "updated_at": "2019-03-20T14:02:22-04:00",
      "active": true,
      "bats": "bats_unknown",
      "birth_date": null,
      "captain": null,
      "city": null,
      "country": "",
      "draft_overall_pick": null,
      "draft_round": null,
      "draft_season": null,
      "draft_team_name": null,
      "first_name": "Robert",
      "handedness": "unknown",
      "height": null,
      "high_school": null,
      "humanized_salary": "0",
      "last_name": "Dalbec",
      "mlbam_id": null,
      "name": "",
      "nickname": "Bobby",
      "position_abbreviation": "IF",
      "position_name": "IF",
      "pro_debut": null,
      "salary": null,
      "salary_currency": "USD",
      "school": null,
      "slug": "mlb-a5cbeb60-a0c4-4456-a5d9-f3d52339d389",
      "sport": "baseball",
      "state": "",
      "uniform_number": "83",
      "unit_of_height": "inches",
      "unit_of_weight": "pounds",
      "weight": null,
      "years_of_experience": null,
      "league_id": "cb399a17-e581-4f1a-9535-ea3bcb09fa1f",
      "playing_position_id": null,
      "team_id": "4c2ad3df-a7fd-458d-a412-6e31574a0b7b"
    },
    {
      "id": "26447c41-a175-4525-8160-c8ce723fef94",
      "created_at": "2016-07-14T02:26:23-04:00",
      "updated_at": "2019-03-20T14:02:17-04:00",
      "active": true,
      "bats": "bats_unknown",
      "birth_date": null,
      "captain": null,
      "city": null,
      "country": "",
      "draft_overall_pick": null,
      "draft_round": null,
      "draft_season": null,
      "draft_team_name": null,
      "first_name": "Chad",
      "handedness": "unknown",
      "height": null,
      "high_school": null,
      "humanized_salary": "0",
      "last_name": "De La Guerra",
      "mlbam_id": null,
      "name": "",
      "nickname": "Chad",
      "position_abbreviation": "IF",
      "position_name": "IF",
      "pro_debut": null,
      "salary": null,
      "salary_currency": "USD",
      "school": null,
      "slug": "chad-de-la-guerra",
      "sport": "baseball",
      "state": "",
      "uniform_number": "74",
      "unit_of_height": "inches",
      "unit_of_weight": "pounds",
      "weight": null,
      "years_of_experience": null,
      "league_id": "cb399a17-e581-4f1a-9535-ea3bcb09fa1f",
      "playing_position_id": null,
      "team_id": "4c2ad3df-a7fd-458d-a412-6e31574a0b7b"
    },
    {
      "id": "b7eadc5f-ffc9-471b-8c13-9a1cdd15a254",
      "created_at": "2016-07-14T02:26:25-04:00",
      "updated_at": "2019-04-19T20:14:34-04:00",
      "active": true,
      "bats": "bats_left",
      "birth_date": "1996-10-24",
      "captain": null,
      "city": "Sanchez",
      "country": "",
      "draft_overall_pick": null,
      "draft_round": null,
      "draft_season": null,
      "draft_team_name": null,
      "first_name": "Rafael",
      "handedness": "right",
      "height": 72,
      "high_school": null,
      "humanized_salary": "0",
      "last_name": "Devers",
      "mlbam_id": 646240,
      "name": "",
      "nickname": "Rafael",
      "position_abbreviation": "IF",
      "position_name": "IF",
      "pro_debut": "2017-07-25",
      "salary": null,
      "salary_currency": "USD",
      "school": null,
      "slug": "mlb-rafael-devers",
      "sport": "baseball",
      "state": "",
      "uniform_number": "11",
      "unit_of_height": "inches",
      "unit_of_weight": "pounds",
      "weight": 237,
      "years_of_experience": null,
      "league_id": "cb399a17-e581-4f1a-9535-ea3bcb09fa1f",
      "playing_position_id": null,
      "team_id": "4c2ad3df-a7fd-458d-a412-6e31574a0b7b"
    },
    {
      "id": "faf76c65-e505-4fec-93ae-9387c04acb33",
      "created_at": "2019-03-04T15:29:49-05:00",
      "updated_at": "2019-03-27T14:04:45-04:00",
      "active": true,
      "bats": "bats_unknown",
      "birth_date": null,
      "captain": null,
      "city": null,
      "country": "",
      "draft_overall_pick": null,
      "draft_round": null,
      "draft_season": null,
      "draft_team_name": null,
      "first_name": "Jarren",
      "handedness": "unknown",
      "height": null,
      "high_school": null,
      "humanized_salary": "0",
      "last_name": "Duran",
      "mlbam_id": null,
      "name": "",
      "nickname": "Jarren",
      "position_abbreviation": "OF",
      "position_name": "OF",
      "pro_debut": null,
      "salary": null,
      "salary_currency": "USD",
      "school": null,
      "slug": "mlb-c748359f-9069-4ae8-86ab-06903949165f",
      "sport": "baseball",
      "state": "",
      "uniform_number": "11",
      "unit_of_height": "inches",
      "unit_of_weight": "pounds",
      "weight": null,
      "years_of_experience": null,
      "league_id": "cb399a17-e581-4f1a-9535-ea3bcb09fa1f",
      "playing_position_id": null,
      "team_id": "4c2ad3df-a7fd-458d-a412-6e31574a0b7b"
    },
    {
      "id": "758d7904-c5b7-4432-88e4-497a6feb2e82",
      "created_at": "2016-03-18T21:11:34-04:00",
      "updated_at": "2019-03-11T14:01:48-04:00",
      "active": true,
      "bats": "bats_right",
      "birth_date": "1990-08-04",
      "captain": null,
      "city": "Gainesville",
      "country": "",
      "draft_overall_pick": 497,
      "draft_round": 16,
      "draft_season": "2012",
      "draft_team_name": "Miami",
      "first_name": "Brian",
      "handedness": "right",
      "height": 76,
      "high_school": "Oak Hall Prep",
      "humanized_salary": "507,500",
      "last_name": "Ellington",
      "mlbam_id": 623395,
      "name": "",
      "nickname": "Brian",
      "position_abbreviation": "RP",
      "position_name": "Reliever",
      "pro_debut": "2015-08-03",
      "salary": 507500,
      "salary_currency": "USD",
      "school": "West Florida",
      "slug": "mlb-brian-ellington",
      "sport": "baseball",
      "state": "",
      "uniform_number": "49",
      "unit_of_height": "inches",
      "unit_of_weight": "pounds",
      "weight": 195,
      "years_of_experience": 1,
      "league_id": "cb399a17-e581-4f1a-9535-ea3bcb09fa1f",
      "playing_position_id": "e895b7e6-2178-41d8-8666-bb4c1bedd2ad",
      "team_id": "4c2ad3df-a7fd-458d-a412-6e31574a0b7b"
    },
    {
      "id": "b0f879d0-0b69-44fb-ae53-15431b511121",
      "created_at": "2016-03-18T21:11:08-04:00",
      "updated_at": "2019-04-19T20:14:33-04:00",
      "active": true,
      "bats": "bats_right",
      "birth_date": "1990-02-13",
      "captain": null,
      "city": "Houston",
      "country": "",
      "draft_overall_pick": 337,
      "draft_round": 10,
      "draft_season": "2008",
      "draft_team_name": "Los Angeles Dodgers",
      "first_name": "Nathan",
      "handedness": "right",
      "height": 74,
      "high_school": "Alvin, TX",
      "humanized_salary": "5,600,000",
      "last_name": "Eovaldi",
      "mlbam_id": 543135,
      "name": "",
      "nickname": "Nathan",
      "position_abbreviation": "SP",
      "position_name": "Starter",
      "pro_debut": "2011-08-06",
      "salary": 5600000,
      "salary_currency": "USD",
      "school": null,
      "slug": "mlb-nathan-eovaldi",
      "sport": "baseball",
      "state": "",
      "uniform_number": "17",
      "unit_of_height": "inches",
      "unit_of_weight": "pounds",
      "weight": 225,
      "years_of_experience": 4,
      "league_id": "cb399a17-e581-4f1a-9535-ea3bcb09fa1f",
      "playing_position_id": "738ffd4a-154d-4ccf-9f9a-5ee32466c4d6",
      "team_id": "4c2ad3df-a7fd-458d-a412-6e31574a0b7b"
    },
    {
      "id": "4a31e293-2fda-45f9-91a9-0dd9b086862c",
      "created_at": "2019-02-27T15:13:38-05:00",
      "updated_at": "2019-03-04T13:08:54-05:00",
      "active": true,
      "bats": "bats_unknown",
      "birth_date": null,
      "captain": null,
      "city": null,
      "country": "",
      "draft_overall_pick": null,
      "draft_round": null,
      "draft_season": null,
      "draft_team_name": null,
      "first_name": "Tyler",
      "handedness": "unknown",
      "height": null,
      "high_school": null,
      "humanized_salary": "0",
      "last_name": "Esplin",
      "mlbam_id": null,
      "name": "",
      "nickname": "Tyler",
      "position_abbreviation": "OF",
      "position_name": "OF",
      "pro_debut": null,
      "salary": null,
      "salary_currency": "USD",
      "school": null,
      "slug": "mlb-5a6f749c-6c52-493a-afb0-ccf30745f82a",
      "sport": "baseball",
      "state": "",
      "uniform_number": "30",
      "unit_of_height": "inches",
      "unit_of_weight": "pounds",
      "weight": null,
      "years_of_experience": null,
      "league_id": "cb399a17-e581-4f1a-9535-ea3bcb09fa1f",
      "playing_position_id": null,
      "team_id": "4c2ad3df-a7fd-458d-a412-6e31574a0b7b"
    },
    {
      "id": "ee547eae-47df-4b88-ac1b-29f70e9c0900",
      "created_at": "2019-03-14T15:56:19-04:00",
      "updated_at": "2019-03-19T14:01:09-04:00",
      "active": true,
      "bats": "bats_unknown",
      "birth_date": null,
      "captain": null,
      "city": null,
      "country": "",
      "draft_overall_pick": null,
      "draft_round": null,
      "draft_season": null,
      "draft_team_name": null,
      "first_name": "Durbin",
      "handedness": "unknown",
      "height": null,
      "high_school": null,
      "humanized_salary": "0",
      "last_name": "Feltman",
      "mlbam_id": null,
      "name": "",
      "nickname": "Durbin",
      "position_abbreviation": "P",
      "position_name": "P",
      "pro_debut": null,
      "salary": null,
      "salary_currency": "USD",
      "school": null,
      "slug": "mlb-ce930e2e-c0de-4510-b755-37f6afa2f3cb",
      "sport": "baseball",
      "state": "",
      "uniform_number": "70",
      "unit_of_height": "inches",
      "unit_of_weight": "pounds",
      "weight": null,
      "years_of_experience": null,
      "league_id": "cb399a17-e581-4f1a-9535-ea3bcb09fa1f",
      "playing_position_id": null,
      "team_id": "4c2ad3df-a7fd-458d-a412-6e31574a0b7b"
    },
    {
      "id": "27c3fda2-a1e7-4d30-a358-4a6c68f97758",
      "created_at": "2019-03-15T15:46:49-04:00",
      "updated_at": "2019-03-20T14:02:07-04:00",
      "active": true,
      "bats": "bats_unknown",
      "birth_date": null,
      "captain": null,
      "city": null,
      "country": "",
      "draft_overall_pick": null,
      "draft_round": null,
      "draft_season": null,
      "draft_team_name": null,
      "first_name": "Ryan",
      "handedness": "unknown",
      "height": null,
      "high_school": null,
      "humanized_salary": "0",
      "last_name": "Fitzgerald",
      "mlbam_id": null,
      "name": "",
      "nickname": "Ryan",
      "position_abbreviation": "IF",
      "position_name": "IF",
      "pro_debut": null,
      "salary": null,
      "salary_currency": "USD",
      "school": null,
      "slug": "mlb-0d53d5cc-82ed-4d18-b7c0-1a7beae15780",
      "sport": "baseball",
      "state": "",
      "uniform_number": null,
      "unit_of_height": "inches",
      "unit_of_weight": "pounds",
      "weight": null,
      "years_of_experience": null,
      "league_id": "cb399a17-e581-4f1a-9535-ea3bcb09fa1f",
      "playing_position_id": null,
      "team_id": "4c2ad3df-a7fd-458d-a412-6e31574a0b7b"
    },
    {
      "id": "c65e6e57-e2b2-4b27-98c8-8d34b0c54397",
      "created_at": "2018-03-01T15:47:26-05:00",
      "updated_at": "2019-03-12T14:04:16-04:00",
      "active": true,
      "bats": "bats_unknown",
      "birth_date": null,
      "captain": null,
      "city": null,
      "country": "",
      "draft_overall_pick": null,
      "draft_round": null,
      "draft_season": null,
      "draft_team_name": null,
      "first_name": "Matthew",
      "handedness": "unknown",
      "height": null,
      "high_school": null,
      "humanized_salary": "0",
      "last_name": "Gorst",
      "mlbam_id": null,
      "name": "",
      "nickname": "Matthew",
      "position_abbreviation": "P",
      "position_name": "P",
      "pro_debut": null,
      "salary": null,
      "salary_currency": "USD",
      "school": null,
      "slug": "mlb-97a43e25-fb4e-43e9-b484-9c807d1e6ca7",
      "sport": "baseball",
      "state": "",
      "uniform_number": "13",
      "unit_of_height": "inches",
      "unit_of_weight": "pounds",
      "weight": null,
      "years_of_experience": null,
      "league_id": "cb399a17-e581-4f1a-9535-ea3bcb09fa1f",
      "playing_position_id": null,
      "team_id": "4c2ad3df-a7fd-458d-a412-6e31574a0b7b"
    },
    {
      "id": "87dd70c0-e1b2-42df-ad99-50c696bca874",
      "created_at": "2016-03-18T21:10:32-04:00",
      "updated_at": "2019-04-19T20:14:33-04:00",
      "active": true,
      "bats": "bats_right",
      "birth_date": "1989-01-13",
      "captain": null,
      "city": "Spartanburg",
      "country": "",
      "draft_overall_pick": 168,
      "draft_round": 5,
      "draft_season": "2010",
      "draft_team_name": "San Francisco",
      "first_name": "Richard",
      "handedness": "right",
      "height": 76,
      "high_school": "Broome, Spartanburg, SC",
      "humanized_salary": "507,500",
      "last_name": "Hembree",
      "mlbam_id": 592390,
      "name": "",
      "nickname": "Heath",
      "position_abbreviation": "RP",
      "position_name": "Reliever",
      "pro_debut": "2013-09-03",
      "salary": 507500,
      "salary_currency": "USD",
      "school": "College of Charleston",
      "slug": "mlb-heath-hembree",
      "sport": "baseball",
      "state": "",
      "uniform_number": "37",
      "unit_of_height": "inches",
      "unit_of_weight": "pounds",
      "weight": 210,
      "years_of_experience": 1,
      "league_id": "cb399a17-e581-4f1a-9535-ea3bcb09fa1f",
      "playing_position_id": "e895b7e6-2178-41d8-8666-bb4c1bedd2ad",
      "team_id": "4c2ad3df-a7fd-458d-a412-6e31574a0b7b"
    },
    {
      "id": "73d8ff9e-20cd-4d66-b2b2-d196b5e86922",
      "created_at": "2016-03-18T21:12:25-04:00",
      "updated_at": "2019-03-19T14:01:06-04:00",
      "active": true,
      "bats": "bats_right",
      "birth_date": "1993-07-09",
      "captain": null,
      "city": "Punto de Fijo",
      "country": "",
      "draft_overall_pick": null,
      "draft_round": null,
      "draft_season": null,
      "draft_team_name": null,
      "first_name": "Oscar",
      "handedness": "right",
      "height": 73,
      "high_school": null,
      "humanized_salary": "0",
      "last_name": "Hernandez",
      "mlbam_id": 591712,
      "name": "",
      "nickname": "Oscar",
      "position_abbreviation": "C",
      "position_name": "Catcher",
      "pro_debut": "2015-07-12",
      "salary": 0,
      "salary_currency": "USD",
      "school": null,
      "slug": "mlb-oscar-hernandez",
      "sport": "baseball",
      "state": "",
      "uniform_number": "77",
      "unit_of_height": "inches",
      "unit_of_weight": "pounds",
      "weight": 220,
      "years_of_experience": 1,
      "league_id": "cb399a17-e581-4f1a-9535-ea3bcb09fa1f",
      "playing_position_id": "35d2f5d0-7407-48c2-80ca-8e5d25e099d9",
      "team_id": "4c2ad3df-a7fd-458d-a412-6e31574a0b7b"
    },
    {
      "id": "bace54e4-1758-4a9a-98df-c568eecd9670",
      "created_at": "2019-02-23T15:03:00-05:00",
      "updated_at": "2019-03-27T19:35:14-04:00",
      "active": true,
      "bats": "bats_left",
      "birth_date": "1996-12-17",
      "captain": null,
      "city": "Ciudad Bolivar",
      "country": "VEN",
      "draft_overall_pick": null,
      "draft_round": null,
      "draft_season": null,
      "draft_team_name": null,
      "first_name": "Darwinzon",
      "handedness": "left",
      "height": 74,
      "high_school": null,
      "humanized_salary": "0",
      "last_name": "Hernandez",
      "mlbam_id": 650382,
      "name": "Darwinzon Hernandez",
      "nickname": "Darwinzon",
      "position_abbreviation": "P",
      "position_name": "P",
      "pro_debut": null,
      "salary": null,
      "salary_currency": "USD",
      "school": null,
      "slug": "mlb-darwinzon-hernandez",
      "sport": "baseball",
      "state": "",
      "uniform_number": "80",
      "unit_of_height": "inches",
      "unit_of_weight": "pounds",
      "weight": 245,
      "years_of_experience": null,
      "league_id": "cb399a17-e581-4f1a-9535-ea3bcb09fa1f",
      "playing_position_id": null,
      "team_id": "4c2ad3df-a7fd-458d-a412-6e31574a0b7b"
    },
    {
      "id": "026f878c-9036-4171-bdeb-33e2fd18ecb0",
      "created_at": "2016-03-18T21:10:32-04:00",
      "updated_at": "2019-03-28T13:11:06-04:00",
      "active": true,
      "bats": "bats_left",
      "birth_date": "1992-09-06",
      "captain": null,
      "city": "Santiago",
      "country": "DOM",
      "draft_overall_pick": null,
      "draft_round": null,
      "draft_season": null,
      "draft_team_name": null,
      "first_name": "Marco",
      "handedness": "right",
      "height": 72,
      "high_school": null,
      "humanized_salary": "507,500",
      "last_name": "Hern치ndez",
      "mlbam_id": 593523,
      "name": "Marco Hern치ndez",
      "nickname": "Marco",
      "position_abbreviation": "SS",
      "position_name": "Shortstop",
      "pro_debut": "2016-04-17",
      "salary": 507500,
      "salary_currency": "USD",
      "school": null,
      "slug": "mlb-marco-hernandez",
      "sport": "baseball",
      "state": "",
      "uniform_number": "40",
      "unit_of_height": "inches",
      "unit_of_weight": "pounds",
      "weight": 200,
      "years_of_experience": 1,
      "league_id": "cb399a17-e581-4f1a-9535-ea3bcb09fa1f",
      "playing_position_id": "4b5f1bc6-07c1-442b-9228-cd9ff0f5b8d1",
      "team_id": "4c2ad3df-a7fd-458d-a412-6e31574a0b7b"
    },
    {
      "id": "08fdfb6b-bc4e-4b64-a015-8d043177a975",
      "created_at": "2016-07-14T02:12:53-04:00",
      "updated_at": "2019-03-27T14:04:46-04:00",
      "active": true,
      "bats": "bats_right",
      "birth_date": "1987-09-07",
      "captain": null,
      "city": "Guiria",
      "country": "",
      "draft_overall_pick": null,
      "draft_round": null,
      "draft_season": null,
      "draft_team_name": null,
      "first_name": "Gorkys",
      "handedness": "right",
      "height": 73,
      "high_school": null,
      "humanized_salary": "0",
      "last_name": "Hern치ndez",
      "mlbam_id": 491676,
      "name": "",
      "nickname": "Gorkys",
      "position_abbreviation": "OF",
      "position_name": "OF",
      "pro_debut": "2012-05-21",
      "salary": null,
      "salary_currency": "USD",
      "school": null,
      "slug": "gorkys-hernandez",
      "sport": "baseball",
      "state": "",
      "uniform_number": "48",
      "unit_of_height": "inches",
      "unit_of_weight": "pounds",
      "weight": 190,
      "years_of_experience": null,
      "league_id": "cb399a17-e581-4f1a-9535-ea3bcb09fa1f",
      "playing_position_id": null,
      "team_id": "4c2ad3df-a7fd-458d-a412-6e31574a0b7b"
    },
    {
      "id": "dc856e8a-54e6-407d-a1e6-da9233100a63",
      "created_at": "2016-03-18T21:10:32-04:00",
      "updated_at": "2019-04-10T19:35:06-04:00",
      "active": true,
      "bats": "bats_left",
      "birth_date": "1988-06-11",
      "captain": null,
      "city": "Fort Worth",
      "country": "USA",
      "draft_overall_pick": 265,
      "draft_round": 9,
      "draft_season": "2009",
      "draft_team_name": null,
      "first_name": "Brock",
      "handedness": "right",
      "height": 70,
      "high_school": "Stephenville, TX",
      "humanized_salary": "606,000",
      "last_name": "Holt",
      "mlbam_id": 571788,
      "name": "Brock Holt",
      "nickname": "Brock",
      "position_abbreviation": "LF",
      "position_name": "Left Outfield",
      "pro_debut": "2012-09-01",
      "salary": 606000,
      "salary_currency": "USD",
      "school": "Rice",
      "slug": "mlb-brock-holt",
      "sport": "baseball",
      "state": "TX",
      "uniform_number": "12",
      "unit_of_height": "inches",
      "unit_of_weight": "pounds",
      "weight": 180,
      "years_of_experience": 5,
      "league_id": "cb399a17-e581-4f1a-9535-ea3bcb09fa1f",
      "playing_position_id": "2d8bfb25-df10-491b-b6b8-e08e173c65e5",
      "team_id": "4c2ad3df-a7fd-458d-a412-6e31574a0b7b"
    },
    {
      "id": "f711d709-3e52-472d-94dc-530b7e9e8a3f",
      "created_at": "2018-02-27T20:57:58-05:00",
      "updated_at": "2019-03-01T13:07:40-05:00",
      "active": true,
      "bats": "bats_unknown",
      "birth_date": null,
      "captain": null,
      "city": null,
      "country": "",
      "draft_overall_pick": null,
      "draft_round": null,
      "draft_season": null,
      "draft_team_name": null,
      "first_name": "Dedgar",
      "handedness": "unknown",
      "height": null,
      "high_school": null,
      "humanized_salary": "0",
      "last_name": "Jimenez",
      "mlbam_id": null,
      "name": "",
      "nickname": "Dedgar",
      "position_abbreviation": "P",
      "position_name": "P",
      "pro_debut": null,
      "salary": null,
      "salary_currency": "USD",
      "school": null,
      "slug": "mlb-5006c277-2026-4375-ab75-d1d0fcf6fc48",
      "sport": "baseball",
      "state": "",
      "uniform_number": null,
      "unit_of_height": "inches",
      "unit_of_weight": "pounds",
      "weight": null,
      "years_of_experience": null,
      "league_id": "cb399a17-e581-4f1a-9535-ea3bcb09fa1f",
      "playing_position_id": null,
      "team_id": "4c2ad3df-a7fd-458d-a412-6e31574a0b7b"
    },
    {
      "id": "38d30dd3-e8f3-4ca1-8a91-0bd46258ea76",
      "created_at": "2016-03-18T21:10:32-04:00",
      "updated_at": "2019-04-10T19:35:07-04:00",
      "active": true,
      "bats": "bats_left",
      "birth_date": "1990-12-07",
      "captain": null,
      "city": "Lakeland",
      "country": "USA",
      "draft_overall_pick": 31,
      "draft_round": 1,
      "draft_season": "2012",
      "draft_team_name": "Boston",
      "first_name": "Christopher",
      "handedness": "left",
      "height": 76,
      "high_school": "Cocoa Beach, FL, USA",
      "humanized_salary": "0",
      "last_name": "Johnson",
      "mlbam_id": 598271,
      "name": "Brian Johnson",
      "nickname": "Brian",
      "position_abbreviation": "SP",
      "position_name": "Starter",
      "pro_debut": "2015-07-21",
      "salary": 0,
      "salary_currency": "USD",
      "school": "Florida",
      "slug": "mlb-brian-johnson",
      "sport": "baseball",
      "state": "FL",
      "uniform_number": "61",
      "unit_of_height": "inches",
      "unit_of_weight": "pounds",
      "weight": 235,
      "years_of_experience": 1,
      "league_id": "cb399a17-e581-4f1a-9535-ea3bcb09fa1f",
      "playing_position_id": "738ffd4a-154d-4ccf-9f9a-5ee32466c4d6",
      "team_id": "4c2ad3df-a7fd-458d-a412-6e31574a0b7b"
    },
    {
      "id": "f31f8b00-6b07-4311-9ff3-10cf4ea14ed9",
      "created_at": "2017-03-19T17:19:04-04:00",
      "updated_at": "2019-03-27T14:04:39-04:00",
      "active": true,
      "bats": "bats_right",
      "birth_date": "1993-10-20",
      "captain": null,
      "city": "Providence",
      "country": "",
      "draft_overall_pick": null,
      "draft_round": null,
      "draft_season": null,
      "draft_team_name": null,
      "first_name": "Trevor",
      "handedness": "right",
      "height": 74,
      "high_school": null,
      "humanized_salary": "0",
      "last_name": "Kelley",
      "mlbam_id": 665001,
      "name": "",
      "nickname": "Trevor",
      "position_abbreviation": "IF",
      "position_name": "IF",
      "pro_debut": null,
      "salary": null,
      "salary_currency": "USD",
      "school": "North Carolina",
      "slug": "mlb-trevor-kelley",
      "sport": "baseball",
      "state": "",
      "uniform_number": "54",
      "unit_of_height": "inches",
      "unit_of_weight": "pounds",
      "weight": 210,
      "years_of_experience": null,
      "league_id": "cb399a17-e581-4f1a-9535-ea3bcb09fa1f",
      "playing_position_id": null,
      "team_id": "4c2ad3df-a7fd-458d-a412-6e31574a0b7b"
    },
    {
      "id": "a81b8ecb-0d5f-4292-b915-c4885cc2ed9e",
      "created_at": "2019-02-23T15:03:00-05:00",
      "updated_at": "2019-03-13T19:35:11-04:00",
      "active": true,
      "bats": "bats_right",
      "birth_date": "1994-06-29",
      "captain": null,
      "city": "Franklin",
      "country": "USA",
      "draft_overall_pick": null,
      "draft_round": null,
      "draft_season": null,
      "draft_team_name": null,
      "first_name": "Travis",
      "handedness": "right",
      "height": 73,
      "high_school": null,
      "humanized_salary": "0",
      "last_name": "Lakins",
      "mlbam_id": 664042,
      "name": "Travis Lakins",
      "nickname": "Travis",
      "position_abbreviation": "P",
      "position_name": "P",
      "pro_debut": null,
      "salary": null,
      "salary_currency": "USD",
      "school": "Ohio State",
      "slug": "mlb-travis-lakins",
      "sport": "baseball",
      "state": "OH",
      "uniform_number": "78",
      "unit_of_height": "inches",
      "unit_of_weight": "pounds",
      "weight": 180,
      "years_of_experience": null,
      "league_id": "cb399a17-e581-4f1a-9535-ea3bcb09fa1f",
      "playing_position_id": null,
      "team_id": "4c2ad3df-a7fd-458d-a412-6e31574a0b7b"
    },
    {
      "id": "c56994f4-0213-4004-98e8-2d2c516300b5",
      "created_at": "2019-03-04T15:29:50-05:00",
      "updated_at": "2019-03-27T14:04:48-04:00",
      "active": true,
      "bats": "bats_unknown",
      "birth_date": null,
      "captain": null,
      "city": null,
      "country": "",
      "draft_overall_pick": null,
      "draft_round": null,
      "draft_season": null,
      "draft_team_name": null,
      "first_name": "Adam",
      "handedness": "unknown",
      "height": null,
      "high_school": null,
      "humanized_salary": "0",
      "last_name": "Lau",
      "mlbam_id": null,
      "name": "",
      "nickname": "Adam",
      "position_abbreviation": "P",
      "position_name": "P",
      "pro_debut": null,
      "salary": null,
      "salary_currency": "USD",
      "school": null,
      "slug": "mlb-dfcc688a-4694-49c2-9c33-2cf65f6b70b5",
      "sport": "baseball",
      "state": "",
      "uniform_number": null,
      "unit_of_height": "inches",
      "unit_of_weight": "pounds",
      "weight": null,
      "years_of_experience": null,
      "league_id": "cb399a17-e581-4f1a-9535-ea3bcb09fa1f",
      "playing_position_id": null,
      "team_id": "4c2ad3df-a7fd-458d-a412-6e31574a0b7b"
    },
    {
      "id": "ff162838-c4f7-4119-80b4-1849045442c9",
      "created_at": "2016-03-18T21:10:02-04:00",
      "updated_at": "2019-04-19T20:14:33-04:00",
      "active": true,
      "bats": "bats_switch",
      "birth_date": "1989-03-13",
      "captain": null,
      "city": "Maracaibo",
      "country": "",
      "draft_overall_pick": null,
      "draft_round": null,
      "draft_season": null,
      "draft_team_name": null,
      "first_name": "Sandy",
      "handedness": "right",
      "height": 70,
      "high_school": null,
      "humanized_salary": "534,000",
      "last_name": "Le칩n",
      "mlbam_id": 506702,
      "name": "",
      "nickname": "Sandy",
      "position_abbreviation": "C",
      "position_name": "Catcher",
      "pro_debut": "2012-05-14",
      "salary": 534000,
      "salary_currency": "USD",
      "school": null,
      "slug": "mlb-sandy-leon",
      "sport": "baseball",
      "state": "",
      "uniform_number": "3",
      "unit_of_height": "inches",
      "unit_of_weight": "pounds",
      "weight": 225,
      "years_of_experience": 3,
      "league_id": "cb399a17-e581-4f1a-9535-ea3bcb09fa1f",
      "playing_position_id": "35d2f5d0-7407-48c2-80ca-8e5d25e099d9",
      "team_id": "4c2ad3df-a7fd-458d-a412-6e31574a0b7b"
    },
    {
      "id": "f9e46539-eed5-4324-b0c4-27481fc57e8b",
      "created_at": "2016-07-14T02:27:25-04:00",
      "updated_at": "2019-04-19T20:14:33-04:00",
      "active": true,
      "bats": "bats_left",
      "birth_date": "1994-02-15",
      "captain": null,
      "city": "Kaohsiung County",
      "country": "",
      "draft_overall_pick": null,
      "draft_round": null,
      "draft_season": null,
      "draft_team_name": null,
      "first_name": "Tzu-Wei",
      "handedness": "right",
      "height": 69,
      "high_school": null,
      "humanized_salary": "0",
      "last_name": "Lin",
      "mlbam_id": 624407,
      "name": "",
      "nickname": "Tzu-Wei",
      "position_abbreviation": "IF",
      "position_name": "IF",
      "pro_debut": "2017-06-24",
      "salary": null,
      "salary_currency": "USD",
      "school": null,
      "slug": "tzu-wei-lin",
      "sport": "baseball",
      "state": "",
      "uniform_number": "5",
      "unit_of_height": "inches",
      "unit_of_weight": "pounds",
      "weight": 155,
      "years_of_experience": null,
      "league_id": "cb399a17-e581-4f1a-9535-ea3bcb09fa1f",
      "playing_position_id": null,
      "team_id": "4c2ad3df-a7fd-458d-a412-6e31574a0b7b"
    },
    {
      "id": "84a41fa2-8779-496e-843f-b6d7691fd6d9",
      "created_at": "2018-03-01T15:47:26-05:00",
      "updated_at": "2019-03-27T14:04:31-04:00",
      "active": true,
      "bats": "bats_unknown",
      "birth_date": null,
      "captain": null,
      "city": null,
      "country": "",
      "draft_overall_pick": null,
      "draft_round": null,
      "draft_season": null,
      "draft_team_name": null,
      "first_name": "Nicholas",
      "handedness": "unknown",
      "height": null,
      "high_school": null,
      "humanized_salary": "0",
      "last_name": "Lovullo",
      "mlbam_id": null,
      "name": "",
      "nickname": "Nick",
      "position_abbreviation": "IF",
      "position_name": "IF",
      "pro_debut": null,
      "salary": null,
      "salary_currency": "USD",
      "school": null,
      "slug": "mlb-5f0f1f86-57a5-4cd3-9aa8-47a0c8faf5ac",
      "sport": "baseball",
      "state": "",
      "uniform_number": "18",
      "unit_of_height": "inches",
      "unit_of_weight": "pounds",
      "weight": null,
      "years_of_experience": null,
      "league_id": "cb399a17-e581-4f1a-9535-ea3bcb09fa1f",
      "playing_position_id": null,
      "team_id": "4c2ad3df-a7fd-458d-a412-6e31574a0b7b"
    },
    {
      "id": "855e6675-15d4-4b1a-a344-753ab845f5e2",
      "created_at": "2018-03-26T20:36:49-04:00",
      "updated_at": "2019-03-23T14:02:46-04:00",
      "active": true,
      "bats": "bats_unknown",
      "birth_date": null,
      "captain": null,
      "city": null,
      "country": "",
      "draft_overall_pick": null,
      "draft_round": null,
      "draft_season": null,
      "draft_team_name": null,
      "first_name": "Christopher",
      "handedness": "unknown",
      "height": null,
      "high_school": null,
      "humanized_salary": "0",
      "last_name": "Madera",
      "mlbam_id": null,
      "name": "",
      "nickname": "Chris",
      "position_abbreviation": "OF",
      "position_name": "OF",
      "pro_debut": null,
      "salary": null,
      "salary_currency": "USD",
      "school": null,
      "slug": "mlb-dabdd902-59d6-43ce-828f-25801ac76531",
      "sport": "baseball",
      "state": "",
      "uniform_number": null,
      "unit_of_height": "inches",
      "unit_of_weight": "pounds",
      "weight": null,
      "years_of_experience": null,
      "league_id": "cb399a17-e581-4f1a-9535-ea3bcb09fa1f",
      "playing_position_id": null,
      "team_id": "4c2ad3df-a7fd-458d-a412-6e31574a0b7b"
    },
    {
      "id": "4283f7b9-b677-4596-be05-cd7871958245",
      "created_at": "2016-07-14T02:23:53-04:00",
      "updated_at": "2019-03-19T14:01:10-04:00",
      "active": true,
      "bats": "bats_unknown",
      "birth_date": null,
      "captain": null,
      "city": null,
      "country": "",
      "draft_overall_pick": null,
      "draft_round": null,
      "draft_season": null,
      "draft_team_name": null,
      "first_name": "Danny",
      "handedness": "unknown",
      "height": null,
      "high_school": null,
      "humanized_salary": "0",
      "last_name": "Mars",
      "mlbam_id": null,
      "name": "",
      "nickname": "Danny",
      "position_abbreviation": "OF",
      "position_name": "OF",
      "pro_debut": null,
      "salary": null,
      "salary_currency": "USD",
      "school": null,
      "slug": "danny-mars",
      "sport": "baseball",
      "state": "",
      "uniform_number": "40",
      "unit_of_height": "inches",
      "unit_of_weight": "pounds",
      "weight": null,
      "years_of_experience": null,
      "league_id": "cb399a17-e581-4f1a-9535-ea3bcb09fa1f",
      "playing_position_id": null,
      "team_id": "4c2ad3df-a7fd-458d-a412-6e31574a0b7b"
    }
  ],
  "leagues": [
    {
      "id": "cb399a17-e581-4f1a-9535-ea3bcb09fa1f",
      "created_at": "2016-03-18T20:56:43-04:00",
      "updated_at": "2016-07-12T19:34:12-04:00",
      "abbreviation": "MLB",
      "color": null,
      "minutes_per_period": 1,
      "name": "Major League Baseball",
      "periods": 9,
      "slug": "mlb",
      "sport": "baseball"
    }
  ],
  "playing_positions": [
    {
      "id": "e895b7e6-2178-41d8-8666-bb4c1bedd2ad",
      "created_at": "2016-03-18T21:09:26-04:00",
      "updated_at": "2016-03-18T21:09:26-04:00",
      "abbreviation": "RP",
      "description": null,
      "formation": "offensive",
      "name": "Reliever",
      "league_id": "cb399a17-e581-4f1a-9535-ea3bcb09fa1f"
    },
    {
      "id": "77303dac-3e19-4c49-802c-eef8719d26cf",
      "created_at": "2016-03-18T21:09:28-04:00",
      "updated_at": "2016-03-18T21:09:28-04:00",
      "abbreviation": "RF",
      "description": null,
      "formation": "offensive",
      "name": "Right Outfield",
      "league_id": "cb399a17-e581-4f1a-9535-ea3bcb09fa1f"
    },
    {
      "id": "4b5f1bc6-07c1-442b-9228-cd9ff0f5b8d1",
      "created_at": "2016-03-18T21:09:26-04:00",
      "updated_at": "2016-03-18T21:09:26-04:00",
      "abbreviation": "SS",
      "description": null,
      "formation": "offensive",
      "name": "Shortstop",
      "league_id": "cb399a17-e581-4f1a-9535-ea3bcb09fa1f"
    },
    {
      "id": "e900e850-ab40-4048-aa57-631ea8390519",
      "created_at": "2016-03-18T21:09:29-04:00",
      "updated_at": "2016-03-18T21:09:29-04:00",
      "abbreviation": "CF",
      "description": null,
      "formation": "offensive",
      "name": "Center Outfield",
      "league_id": "cb399a17-e581-4f1a-9535-ea3bcb09fa1f"
    },
    {
      "id": "35d2f5d0-7407-48c2-80ca-8e5d25e099d9",
      "created_at": "2016-03-18T21:09:27-04:00",
      "updated_at": "2016-03-18T21:09:27-04:00",
      "abbreviation": "C",
      "description": null,
      "formation": "offensive",
      "name": "Catcher",
      "league_id": "cb399a17-e581-4f1a-9535-ea3bcb09fa1f"
    },
    {
      "id": "738ffd4a-154d-4ccf-9f9a-5ee32466c4d6",
      "created_at": "2016-03-18T21:09:27-04:00",
      "updated_at": "2016-03-18T21:09:27-04:00",
      "abbreviation": "SP",
      "description": null,
      "formation": "offensive",
      "name": "Starter",
      "league_id": "cb399a17-e581-4f1a-9535-ea3bcb09fa1f"
    },
    {
      "id": "2d8bfb25-df10-491b-b6b8-e08e173c65e5",
      "created_at": "2016-03-18T21:09:29-04:00",
      "updated_at": "2016-03-18T21:09:29-04:00",
      "abbreviation": "LF",
      "description": null,
      "formation": "offensive",
      "name": "Left Outfield",
      "league_id": "cb399a17-e581-4f1a-9535-ea3bcb09fa1f"
    }
  ],
  "teams": [
    {
      "id": "4c2ad3df-a7fd-458d-a412-6e31574a0b7b",
      "created_at": "2016-03-18T20:56:44-04:00",
      "updated_at": "2016-07-12T19:34:14-04:00",
      "abbreviation": "BOS",
      "color": "BD3039",
      "colors": [ "BD3039", "0D2B56" ],
      "hashtag": "RedSox",
      "hashtags": [ "RedSox" ],
      "location": "Boston",
      "name": "Boston",
      "nickname": "Red Sox",
      "latitude": 42.3404226,
      "longitude": -71.0948148,
      "slug": "mlb-bos",
      "division_id": "d4f9e9e2-18fb-4e61-8bfd-32d0e8502e09",
      "league_id": "cb399a17-e581-4f1a-9535-ea3bcb09fa1f"
    }
  ],
  "seasons": [
    {
      "id": "36a3cc89-aa83-4391-b0b5-2bf8905393d8",
      "created_at": "2017-02-14T19:00:00-05:00",
      "updated_at": "2017-03-07T09:02:50-05:00",
      "name": "2019",
      "current_interval_type": "regularseason",
      "starts_on": "2019-02-21",
      "ends_on": "2019-11-30",
      "stats_coverage": "season_stat_and_boxscore_play_by_play",
      "slug": "mlb-2019",
      "league_id": "cb399a17-e581-4f1a-9535-ea3bcb09fa1f"
    }
  ],
  "rosters": [
    {
      "id": "4aaf2828-fa70-4f2d-966c-d7cd5715b51e",
      "created_at": "2019-03-04T16:30:00-05:00",
      "updated_at": "2019-03-04T16:30:00-05:00",
      "last_game_started_at": "2019-03-04T13:10:00-05:00",
      "status": "A",
      "player_id": "731977d7-3863-4ff7-af00-1cc16447f944",
      "team_id": "4c2ad3df-a7fd-458d-a412-6e31574a0b7b",
      "season_id": "36a3cc89-aa83-4391-b0b5-2bf8905393d8"
    },
    {
      "id": "012a5719-67a3-441a-9e25-2b5ea6b32237",
      "created_at": "2019-02-23T15:03:00-05:00",
      "updated_at": "2019-04-17T14:02:55-04:00",
      "last_game_started_at": "2019-04-14T13:05:00-04:00",
      "status": "A",
      "player_id": "6c2978fe-b241-42c7-aa7d-607f1b5bc1cc",
      "team_id": "4c2ad3df-a7fd-458d-a412-6e31574a0b7b",
      "season_id": "36a3cc89-aa83-4391-b0b5-2bf8905393d8"
    },
    {
      "id": "6799f47a-1f38-4503-9324-4f6c64818357",
      "created_at": "2019-02-23T15:03:00-05:00",
      "updated_at": "2019-04-19T19:14:43-04:00",
      "last_game_started_at": "2019-04-19T19:10:00-04:00",
      "status": "A",
      "player_id": "14d3cdd3-422e-4efd-9d0c-b61718ef76f6",
      "team_id": "4c2ad3df-a7fd-458d-a412-6e31574a0b7b",
      "season_id": "36a3cc89-aa83-4391-b0b5-2bf8905393d8"
    },
    {
      "id": "a4123e9d-8456-46e5-b828-4b25aa9037ae",
      "created_at": "2019-02-23T15:03:00-05:00",
      "updated_at": "2019-04-19T19:14:42-04:00",
      "last_game_started_at": "2019-04-19T19:10:00-04:00",
      "status": "A",
      "player_id": "bfca5f98-d7ca-47b9-a7dc-f9848e334cea",
      "team_id": "4c2ad3df-a7fd-458d-a412-6e31574a0b7b",
      "season_id": "36a3cc89-aa83-4391-b0b5-2bf8905393d8"
    },
    {
      "id": "22afc003-03a1-48c1-9e72-fb205c904ccf",
      "created_at": "2019-02-23T15:02:59-05:00",
      "updated_at": "2019-04-19T19:44:39-04:00",
      "last_game_started_at": "2019-04-19T19:10:00-04:00",
      "status": "A",
      "player_id": "88861b5b-76b5-43dc-bbad-b2c2aea72a8a",
      "team_id": "4c2ad3df-a7fd-458d-a412-6e31574a0b7b",
      "season_id": "36a3cc89-aa83-4391-b0b5-2bf8905393d8"
    },
    {
      "id": "b091f666-39cf-4817-ac9d-3dff629ef9dc",
      "created_at": "2019-02-23T15:03:00-05:00",
      "updated_at": "2019-04-19T19:44:39-04:00",
      "last_game_started_at": "2019-04-19T19:10:00-04:00",
      "status": "A",
      "player_id": "bed54f1c-83f5-4373-93d5-a88df57c0550",
      "team_id": "4c2ad3df-a7fd-458d-a412-6e31574a0b7b",
      "season_id": "36a3cc89-aa83-4391-b0b5-2bf8905393d8"
    },
    {
      "id": "1b309b1e-984c-4e0a-8890-ee9dc81a40aa",
      "created_at": "2019-02-23T15:03:00-05:00",
      "updated_at": "2019-04-19T14:02:29-04:00",
      "last_game_started_at": "2019-04-14T13:05:00-04:00",
      "status": "A",
      "player_id": "5f0de0a2-a52e-470e-bcf8-dd59a5c406cf",
      "team_id": "4c2ad3df-a7fd-458d-a412-6e31574a0b7b",
      "season_id": "36a3cc89-aa83-4391-b0b5-2bf8905393d8"
    },
    {
      "id": "94041e12-6c41-4a82-abd7-7b23f09c507e",
      "created_at": "2019-02-28T15:20:12-05:00",
      "updated_at": "2019-03-14T13:26:18-04:00",
      "last_game_started_at": "2019-03-14T13:05:00-04:00",
      "status": "A",
      "player_id": "a0d7b12b-5965-4b36-bbcf-73f4c4849e2a",
      "team_id": "4c2ad3df-a7fd-458d-a412-6e31574a0b7b",
      "season_id": "36a3cc89-aa83-4391-b0b5-2bf8905393d8"
    },
    {
      "id": "cb9a04e7-9dea-48cb-8039-ffd91ef1fba8",
      "created_at": "2019-02-23T15:03:00-05:00",
      "updated_at": "2019-04-18T14:02:40-04:00",
      "last_game_started_at": "2019-04-15T11:05:00-04:00",
      "status": "A",
      "player_id": "45caff13-c86a-48aa-8de5-44da882a05cc",
      "team_id": "4c2ad3df-a7fd-458d-a412-6e31574a0b7b",
      "season_id": "36a3cc89-aa83-4391-b0b5-2bf8905393d8"
    },
    {
      "id": "6654f20f-d8ee-4ea3-923c-137df8660e41",
      "created_at": "2019-02-24T15:04:36-05:00",
      "updated_at": "2019-03-15T15:46:58-04:00",
      "last_game_started_at": "2019-03-15T13:05:00-04:00",
      "status": "A",
      "player_id": "518ca203-58a0-4285-bb3a-6bfb486d7593",
      "team_id": "4c2ad3df-a7fd-458d-a412-6e31574a0b7b",
      "season_id": "36a3cc89-aa83-4391-b0b5-2bf8905393d8"
    },
    {
      "id": "d2f8406f-a8d6-4206-81be-96c7a939fbbf",
      "created_at": "2019-02-27T13:43:01-05:00",
      "updated_at": "2019-03-19T14:01:31-04:00",
      "last_game_started_at": "2019-03-15T13:05:00-04:00",
      "status": "A",
      "player_id": "3fd91bf9-94dd-4184-a157-07f6d5c6b958",
      "team_id": "4c2ad3df-a7fd-458d-a412-6e31574a0b7b",
      "season_id": "36a3cc89-aa83-4391-b0b5-2bf8905393d8"
    },
    {
      "id": "3fb6fe3c-0cea-4efc-a854-34c257fb714b",
      "created_at": "2019-02-23T15:02:59-05:00",
      "updated_at": "2019-04-19T13:16:47-04:00",
      "last_game_started_at": "2019-03-05T13:05:00-05:00",
      "status": "A",
      "player_id": "65301106-5df0-4e45-b95d-62a0893b0b8b",
      "team_id": "4c2ad3df-a7fd-458d-a412-6e31574a0b7b",
      "season_id": "36a3cc89-aa83-4391-b0b5-2bf8905393d8"
    },
    {
      "id": "91b881b5-f09d-4c7a-8618-fd13e564808a",
      "created_at": "2019-02-24T15:54:14-05:00",
      "updated_at": "2019-02-24T15:54:14-05:00",
      "last_game_started_at": "2019-02-24T13:05:00-05:00",
      "status": "A",
      "player_id": "01a04264-958e-4f0e-bc69-16e9c1f07cbb",
      "team_id": "4c2ad3df-a7fd-458d-a412-6e31574a0b7b",
      "season_id": "36a3cc89-aa83-4391-b0b5-2bf8905393d8"
    },
    {
      "id": "63b41f0a-4b0b-415e-a199-cdb4ac8eb31b",
      "created_at": "2019-02-27T16:13:33-05:00",
      "updated_at": "2019-02-27T16:13:33-05:00",
      "last_game_started_at": "2019-02-27T13:05:00-05:00",
      "status": "A",
      "player_id": "07000391-d992-4741-9657-45f515ce0cd6",
      "team_id": "4c2ad3df-a7fd-458d-a412-6e31574a0b7b",
      "season_id": "36a3cc89-aa83-4391-b0b5-2bf8905393d8"
    },
    {
      "id": "f4a9a535-567f-4c2d-90bc-f30d0ead3244",
      "created_at": "2019-02-24T14:34:36-05:00",
      "updated_at": "2019-03-19T14:01:26-04:00",
      "last_game_started_at": "2019-03-15T13:05:00-04:00",
      "status": "A",
      "player_id": "00ffaeee-8275-466f-ba59-cd69df4ba179",
      "team_id": "4c2ad3df-a7fd-458d-a412-6e31574a0b7b",
      "season_id": "36a3cc89-aa83-4391-b0b5-2bf8905393d8"
    },
    {
      "id": "3e377617-5eea-4df9-9571-420e54bdbb2a",
      "created_at": "2019-02-24T14:34:35-05:00",
      "updated_at": "2019-03-19T14:01:20-04:00",
      "last_game_started_at": "2019-03-15T13:05:00-04:00",
      "status": "A",
      "player_id": "26447c41-a175-4525-8160-c8ce723fef94",
      "team_id": "4c2ad3df-a7fd-458d-a412-6e31574a0b7b",
      "season_id": "36a3cc89-aa83-4391-b0b5-2bf8905393d8"
    },
    {
      "id": "86bfc775-407f-4293-a250-bdb5029b82ac",
      "created_at": "2019-02-23T15:02:59-05:00",
      "updated_at": "2019-04-19T19:44:41-04:00",
      "last_game_started_at": "2019-04-19T19:10:00-04:00",
      "status": "A",
      "player_id": "b7eadc5f-ffc9-471b-8c13-9a1cdd15a254",
      "team_id": "4c2ad3df-a7fd-458d-a412-6e31574a0b7b",
      "season_id": "36a3cc89-aa83-4391-b0b5-2bf8905393d8"
    },
    {
      "id": "1df9ec40-b550-4317-8ee9-aa9e8f1fd822",
      "created_at": "2019-03-04T15:29:55-05:00",
      "updated_at": "2019-03-22T19:47:52-04:00",
      "last_game_started_at": "2019-03-22T18:05:00-04:00",
      "status": "A",
      "player_id": "faf76c65-e505-4fec-93ae-9387c04acb33",
      "team_id": "4c2ad3df-a7fd-458d-a412-6e31574a0b7b",
      "season_id": "36a3cc89-aa83-4391-b0b5-2bf8905393d8"
    },
    {
      "id": "3fe5e239-ccd0-4b7d-975b-a1c28b89112b",
      "created_at": "2019-02-27T15:43:30-05:00",
      "updated_at": "2019-03-10T07:01:08-04:00",
      "last_game_started_at": "2019-03-06T13:05:00-05:00",
      "status": "A",
      "player_id": "758d7904-c5b7-4432-88e4-497a6feb2e82",
      "team_id": "4c2ad3df-a7fd-458d-a412-6e31574a0b7b",
      "season_id": "36a3cc89-aa83-4391-b0b5-2bf8905393d8"
    },
    {
      "id": "5eddc3bf-5d5a-41a5-86fe-6df04f282995",
      "created_at": "2019-02-23T15:03:00-05:00",
      "updated_at": "2019-04-17T18:47:36-04:00",
      "last_game_started_at": "2019-04-17T18:35:00-04:00",
      "status": "A",
      "player_id": "b0f879d0-0b69-44fb-ae53-15431b511121",
      "team_id": "4c2ad3df-a7fd-458d-a412-6e31574a0b7b",
      "season_id": "36a3cc89-aa83-4391-b0b5-2bf8905393d8"
    },
    {
      "id": "94ac1db0-3f36-4d33-850f-bfaeda13263d",
      "created_at": "2019-02-27T15:13:52-05:00",
      "updated_at": "2019-02-27T15:13:52-05:00",
      "last_game_started_at": "2019-02-27T13:05:00-05:00",
      "status": "A",
      "player_id": "4a31e293-2fda-45f9-91a9-0dd9b086862c",
      "team_id": "4c2ad3df-a7fd-458d-a412-6e31574a0b7b",
      "season_id": "36a3cc89-aa83-4391-b0b5-2bf8905393d8"
    },
    {
      "id": "03263642-5219-40ce-8a74-8d74b15935e6",
      "created_at": "2019-03-14T15:56:25-04:00",
      "updated_at": "2019-03-14T15:56:25-04:00",
      "last_game_started_at": "2019-03-14T13:05:00-04:00",
      "status": "A",
      "player_id": "ee547eae-47df-4b88-ac1b-29f70e9c0900",
      "team_id": "4c2ad3df-a7fd-458d-a412-6e31574a0b7b",
      "season_id": "36a3cc89-aa83-4391-b0b5-2bf8905393d8"
    },
    {
      "id": "d563aa70-353c-400f-8658-68bee6a3b4b6",
      "created_at": "2019-03-15T15:46:54-04:00",
      "updated_at": "2019-03-15T15:46:54-04:00",
      "last_game_started_at": "2019-03-15T13:05:00-04:00",
      "status": "A",
      "player_id": "27c3fda2-a1e7-4d30-a358-4a6c68f97758",
      "team_id": "4c2ad3df-a7fd-458d-a412-6e31574a0b7b",
      "season_id": "36a3cc89-aa83-4391-b0b5-2bf8905393d8"
    },
    {
      "id": "25e39222-225c-496a-9261-405fcd0e998c",
      "created_at": "2019-02-24T15:24:13-05:00",
      "updated_at": "2019-03-10T07:00:42-04:00",
      "last_game_started_at": "2019-03-07T13:05:00-05:00",
      "status": "A",
      "player_id": "c65e6e57-e2b2-4b27-98c8-8d34b0c54397",
      "team_id": "4c2ad3df-a7fd-458d-a412-6e31574a0b7b",
      "season_id": "36a3cc89-aa83-4391-b0b5-2bf8905393d8"
    },
    {
      "id": "1352989b-92c1-4e82-9228-24520e6d4492",
      "created_at": "2019-02-23T15:03:00-05:00",
      "updated_at": "2019-04-19T14:03:17-04:00",
      "last_game_started_at": "2019-04-15T11:05:00-04:00",
      "status": "A",
      "player_id": "87dd70c0-e1b2-42df-ad99-50c696bca874",
      "team_id": "4c2ad3df-a7fd-458d-a412-6e31574a0b7b",
      "season_id": "36a3cc89-aa83-4391-b0b5-2bf8905393d8"
    },
    {
      "id": "3b011e65-53d3-48bd-97c9-7518cd80be51",
      "created_at": "2019-02-24T15:04:36-05:00",
      "updated_at": "2019-03-14T14:56:22-04:00",
      "last_game_started_at": "2019-03-14T13:05:00-04:00",
      "status": "A",
      "player_id": "73d8ff9e-20cd-4d66-b2b2-d196b5e86922",
      "team_id": "4c2ad3df-a7fd-458d-a412-6e31574a0b7b",
      "season_id": "36a3cc89-aa83-4391-b0b5-2bf8905393d8"
    },
    {
      "id": "b1c2e65d-0243-416c-855d-a2c8516e9177",
      "created_at": "2019-02-23T15:03:01-05:00",
      "updated_at": "2019-03-23T19:35:09-04:00",
      "last_game_started_at": "2019-03-08T13:05:00-05:00",
      "status": "MIN",
      "player_id": "bace54e4-1758-4a9a-98df-c568eecd9670",
      "team_id": "4c2ad3df-a7fd-458d-a412-6e31574a0b7b",
      "season_id": "36a3cc89-aa83-4391-b0b5-2bf8905393d8"
    },
    {
      "id": "b20c4570-efb8-4005-b9de-8757b7c7c43b",
      "created_at": "2019-02-23T15:02:59-05:00",
      "updated_at": "2019-03-28T13:11:56-04:00",
      "last_game_started_at": null,
      "status": "D10",
      "player_id": "026f878c-9036-4171-bdeb-33e2fd18ecb0",
      "team_id": "4c2ad3df-a7fd-458d-a412-6e31574a0b7b",
      "season_id": "36a3cc89-aa83-4391-b0b5-2bf8905393d8"
    },
    {
      "id": "430ff6cb-8fac-41ad-8ffa-59777ceb9ee5",
      "created_at": "2019-02-27T13:18:10-05:00",
      "updated_at": "2019-03-24T09:10:28-04:00",
      "last_game_started_at": "2019-03-22T18:05:00-04:00",
      "status": "A",
      "player_id": "08fdfb6b-bc4e-4b64-a015-8d043177a975",
      "team_id": "4c2ad3df-a7fd-458d-a412-6e31574a0b7b",
      "season_id": "36a3cc89-aa83-4391-b0b5-2bf8905393d8"
    },
    {
      "id": "7c60cfb2-b415-4df5-ac30-693bac3b3df2",
      "created_at": "2019-02-23T15:03:00-05:00",
      "updated_at": "2019-04-10T19:35:07-04:00",
      "last_game_started_at": "2019-04-05T19:10:00-04:00",
      "status": "D10",
      "player_id": "dc856e8a-54e6-407d-a1e6-da9233100a63",
      "team_id": "4c2ad3df-a7fd-458d-a412-6e31574a0b7b",
      "season_id": "36a3cc89-aa83-4391-b0b5-2bf8905393d8"
    },
    {
      "id": "4ddae008-65aa-49b5-8402-28ddc009bcc5",
      "created_at": "2019-02-24T13:34:40-05:00",
      "updated_at": "2019-02-24T13:34:40-05:00",
      "last_game_started_at": "2019-02-24T13:05:00-05:00",
      "status": "A",
      "player_id": "f711d709-3e52-472d-94dc-530b7e9e8a3f",
      "team_id": "4c2ad3df-a7fd-458d-a412-6e31574a0b7b",
      "season_id": "36a3cc89-aa83-4391-b0b5-2bf8905393d8"
    },
    {
      "id": "d59d6396-6f82-4870-837b-534dd9c5ea17",
      "created_at": "2019-02-23T15:03:01-05:00",
      "updated_at": "2019-04-10T19:35:07-04:00",
      "last_game_started_at": "2019-04-05T19:10:00-04:00",
      "status": "D10",
      "player_id": "38d30dd3-e8f3-4ca1-8a91-0bd46258ea76",
      "team_id": "4c2ad3df-a7fd-458d-a412-6e31574a0b7b",
      "season_id": "36a3cc89-aa83-4391-b0b5-2bf8905393d8"
    },
    {
      "id": "09f73d6a-f0c5-4253-9311-14eeb90235da",
      "created_at": "2019-02-27T14:13:03-05:00",
      "updated_at": "2019-03-22T19:17:35-04:00",
      "last_game_started_at": "2019-03-22T18:05:00-04:00",
      "status": "A",
      "player_id": "f31f8b00-6b07-4311-9ff3-10cf4ea14ed9",
      "team_id": "4c2ad3df-a7fd-458d-a412-6e31574a0b7b",
      "season_id": "36a3cc89-aa83-4391-b0b5-2bf8905393d8"
    },
    {
      "id": "0b124d5e-963a-4341-99b3-3cdebb4a169a",
      "created_at": "2019-02-23T15:03:01-05:00",
      "updated_at": "2019-03-13T19:35:12-04:00",
      "last_game_started_at": "2019-03-08T13:05:00-05:00",
      "status": "MIN",
      "player_id": "a81b8ecb-0d5f-4292-b915-c4885cc2ed9e",
      "team_id": "4c2ad3df-a7fd-458d-a412-6e31574a0b7b",
      "season_id": "36a3cc89-aa83-4391-b0b5-2bf8905393d8"
    },
    {
      "id": "6b1ec385-4b3b-4458-aab2-7bf507a5ba4f",
      "created_at": "2019-03-04T15:29:56-05:00",
      "updated_at": "2019-03-22T21:47:16-04:00",
      "last_game_started_at": "2019-03-22T18:05:00-04:00",
      "status": "A",
      "player_id": "c56994f4-0213-4004-98e8-2d2c516300b5",
      "team_id": "4c2ad3df-a7fd-458d-a412-6e31574a0b7b",
      "season_id": "36a3cc89-aa83-4391-b0b5-2bf8905393d8"
    },
    {
      "id": "2a338b9f-2b37-48ed-9d45-4c2c7a38408d",
      "created_at": "2019-02-23T15:02:59-05:00",
      "updated_at": "2019-04-16T19:07:47-04:00",
      "last_game_started_at": "2019-04-16T18:35:00-04:00",
      "status": "A",
      "player_id": "ff162838-c4f7-4119-80b4-1849045442c9",
      "team_id": "4c2ad3df-a7fd-458d-a412-6e31574a0b7b",
      "season_id": "36a3cc89-aa83-4391-b0b5-2bf8905393d8"
    },
    {
      "id": "123e5e30-f2ef-48dd-a8ea-da01b0d1069e",
      "created_at": "2019-02-23T15:03:00-05:00",
      "updated_at": "2019-04-19T19:44:40-04:00",
      "last_game_started_at": "2019-04-19T19:10:00-04:00",
      "status": "A",
      "player_id": "f9e46539-eed5-4324-b0c4-27481fc57e8b",
      "team_id": "4c2ad3df-a7fd-458d-a412-6e31574a0b7b",
      "season_id": "36a3cc89-aa83-4391-b0b5-2bf8905393d8"
    },
    {
      "id": "bce7d851-b75c-4431-b014-01b53685259b",
      "created_at": "2019-03-14T15:56:21-04:00",
      "updated_at": "2019-03-24T09:09:49-04:00",
      "last_game_started_at": "2019-03-22T18:05:00-04:00",
      "status": "A",
      "player_id": "84a41fa2-8779-496e-843f-b6d7691fd6d9",
      "team_id": "4c2ad3df-a7fd-458d-a412-6e31574a0b7b",
      "season_id": "36a3cc89-aa83-4391-b0b5-2bf8905393d8"
    },
    {
      "id": "0bc6f469-70b7-4e17-ac94-aecaa2b8d3cd",
      "created_at": "2019-03-05T15:35:37-05:00",
      "updated_at": "2019-03-20T14:05:48-04:00",
      "last_game_started_at": "2019-03-18T13:05:00-04:00",
      "status": "A",
      "player_id": "855e6675-15d4-4b1a-a344-753ab845f5e2",
      "team_id": "4c2ad3df-a7fd-458d-a412-6e31574a0b7b",
      "season_id": "36a3cc89-aa83-4391-b0b5-2bf8905393d8"
    },
    {
      "id": "7262f05e-4f7b-4e9a-8fec-b25aa4c380d1",
      "created_at": "2019-02-24T15:04:37-05:00",
      "updated_at": "2019-03-14T15:26:27-04:00",
      "last_game_started_at": "2019-03-14T13:05:00-04:00",
      "status": "A",
      "player_id": "4283f7b9-b677-4596-be05-cd7871958245",
      "team_id": "4c2ad3df-a7fd-458d-a412-6e31574a0b7b",
      "season_id": "36a3cc89-aa83-4391-b0b5-2bf8905393d8"
    }
  ]
}
